{
	"agehama": {
		"black": 0,
		"white": 0
	},
	"cells": [
		[
			0,
			0,
			0,
			0,
			0,
			0,
			0,
			0,
			0
		],
		[
			0,
			0,
			0,
			0,
			0,
			0,
			0,
			0,
			0
		],
		[
			0,
			0,
			0,
			0,
			2,
			2,
			2,
			0,
			0
		],
		[
			0,
			0,
			0,
			2,
			2,
			1,
			1,
			2,
			0
		],
		[
			2,
			2,
			2,
			2,
			1,
			0,
			0,
			1,
			42
		],
		[
			2,
			1,
			1,
			1,
			1,
			0,
			1,
			0,
			0
		],
		[
			1,
			1,
			0,
			0,
			0,
			0,
			0,
			1,
			0
		],
		[
			0,
			0,
			0,
			0,
			0,
			0,
			0,
			0,
			0
		],
		[
			0,
			0,
			0,
			0,
			0,
			0,
			0,
			0,
			0
		]
	],
	"groupId": "問題集 Part 2",
	"handHistory": [
		{
			"number": 1140,
			"options": "",
			"stone": 1,
			"type": "onBoard",
			"x": 6,
			"y": 0
		},
		{
			"number": 1141,
			"options": "",
			"stone": 2,
			"type": "onBoard",
			"x": 5,
			"y": 0
		},
		{
			"number": 1142,
			"options": "",
			"stone": 2,
			"type": "onBoard",
			"x": 4,
			"y": 0
		},
		{
			"number": 1143,
			"options": "",
			"stone": 2,
			"type": "onBoard",
			"x": 4,
			"y": 1
		},
		{
			"number": 1144,
			"options": "",
			"stone": 2,
			"type": "onBoard",
			"x": 4,
			"y": 2
		},
		{
			"number": 1145,
			"options": "",
			"stone": 2,
			"type": "onBoard",
			"x": 4,
			"y": 3
		},
		{
			"number": 1146,
			"options": "",
			"stone": 1,
			"type": "onBoard",
			"x": 5,
			"y": 1
		},
		{
			"number": 1147,
			"options": "",
			"stone": 1,
			"type": "onBoard",
			"x": 5,
			"y": 2
		},
		{
			"number": 1148,
			"options": "",
			"stone": 1,
			"type": "onBoard",
			"x": 5,
			"y": 3
		},
		{
			"number": 1149,
			"options": "",
			"stone": 1,
			"type": "onBoard",
			"x": 5,
			"y": 4
		},
		{
			"number": 1150,
			"options": "",
			"stone": 1,
			"type": "onBoard",
			"x": 6,
			"y": 1
		},
		{
			"number": 1151,
			"options": "",
			"stone": 1,
			"type": "onBoard",
			"x": 4,
			"y": 4
		},
		{
			"number": 1152,
			"options": "",
			"stone": 2,
			"type": "onBoard",
			"x": 3,
			"y": 3
		},
		{
			"number": 1153,
			"options": "",
			"stone": 2,
			"type": "onBoard",
			"x": 3,
			"y": 4
		},
		{
			"number": 1154,
			"options": "",
			"stone": 2,
			"type": "onBoard",
			"x": 2,
			"y": 4
		},
		{
			"number": 1155,
			"options": "",
			"stone": 2,
			"type": "onBoard",
			"x": 2,
			"y": 5
		},
		{
			"number": 1156,
			"options": "",
			"stone": 2,
			"type": "onBoard",
			"x": 2,
			"y": 6
		},
		{
			"number": 1157,
			"options": "",
			"stone": 1,
			"type": "onBoard",
			"x": 3,
			"y": 5
		},
		{
			"number": 1158,
			"options": "",
			"stone": 1,
			"type": "onBoard",
			"x": 3,
			"y": 6
		},
		{
			"number": 1159,
			"options": "",
			"stone": 2,
			"type": "onBoard",
			"x": 3,
			"y": 7
		},
		{
			"number": 1160,
			"options": "",
			"stone": 1,
			"type": "onBoard",
			"x": 4,
			"y": 7
		},
		{
			"number": 1161,
			"options": "",
			"stone": 2,
			"type": "onBoard",
			"x": 4,
			"y": 8
		},
		{
			"number": 1162,
			"options": "",
			"stone": 1,
			"type": "onBoard",
			"x": 5,
			"y": 6
		},
		{
			"number": 1163,
			"options": "",
			"stone": 1,
			"type": "onBoard",
			"x": 6,
			"y": 7
		},
		{
			"number": 1164,
			"options": "",
			"stone": 42,
			"type": "onBoard",
			"x": 4,
			"y": 8
		}
	],
	"message": "\u003Cp\u003E 黒番．白がAと打ってきました．チャンス！\u003C/p\u003E",
	"name": "問題16",
	"problemId": 1496846003726,
	"ro": 9,
	"symbols": {}
}